sphere/IFS.py
sphere/SPARTA.py
sphere/SPHERE.py
sphere/__init__.py
sphere/IRDIS/ImagingReduction.py
sphere/IRDIS/SpectroReduction.py
sphere/IRDIS/__init__.py
sphere/data/SPHERE_CPI_ND.txt
sphere/data/SPHERE_IRDIS_B_H.txt
sphere/data/SPHERE_IRDIS_B_Hcmp2.txt
sphere/data/SPHERE_IRDIS_B_J.txt
sphere/data/SPHERE_IRDIS_B_Ks.txt
sphere/data/SPHERE_IRDIS_B_ND-H.txt
sphere/data/SPHERE_IRDIS_B_Y.txt
sphere/data/SPHERE_IRDIS_D_H23.txt
sphere/data/SPHERE_IRDIS_D_H32.txt
sphere/data/SPHERE_IRDIS_D_H34.txt
sphere/data/SPHERE_IRDIS_D_J23.txt
sphere/data/SPHERE_IRDIS_D_K12.txt
sphere/data/SPHERE_IRDIS_D_Y23.txt
sphere/data/SPHERE_IRDIS_ND.txt
sphere/data/SPHERE_IRDIS_N_BrG.txt
sphere/data/SPHERE_IRDIS_N_CO.txt
sphere/data/SPHERE_IRDIS_N_CntH.txt
sphere/data/SPHERE_IRDIS_N_CntJ.txt
sphere/data/SPHERE_IRDIS_N_CntK1.txt
sphere/data/SPHERE_IRDIS_N_CntK2.txt
sphere/data/SPHERE_IRDIS_N_FeII.txt
sphere/data/SPHERE_IRDIS_N_H2.txt
sphere/data/SPHERE_IRDIS_N_HeI.txt
sphere/data/SPHERE_IRDIS_N_PaB.txt
sphere/data/ifu_mask.fits
sphere/instruments/IFS.ini
sphere/instruments/IRDIS.ini
sphere/instruments/SPARTA.ini
sphere/instruments/keywords_irdifs.dat
sphere/instruments/keywords_sparta.dat
sphere/utils/__init__.py
sphere/utils/aperture.py
sphere/utils/config.py
sphere/utils/imutils.py
sphere/utils/mft.py
sphere/utils/reduction_path.py
sphere/utils/toolbox.py
sphere/utils/transmission.py
vlt_sphere-1.8.dist-info/LICENSE
vlt_sphere-1.8.dist-info/METADATA
vlt_sphere-1.8.dist-info/WHEEL
vlt_sphere-1.8.dist-info/top_level.txt
vlt_sphere-1.8.dist-info/RECORD
