Metadata-Version: 2.1
Name: vlt-sphere
Version: 1.8
Summary: Reduction and analysis code for the VLT/SPHERE instrument
Home-page: https://github.com/avigan/SPHERE
Author: Arthur Vigan
Author-email: arthur.vigan@lam.fr
License: MIT
Keywords: vlt sphere ifs irdis reduction exoplanet pipeline
Classifier: Development Status :: 5 - Production/Stable
Classifier: Intended Audience :: Science/Research 
Classifier: Topic :: Scientific/Engineering :: Astronomy
Classifier: Programming Language :: Python :: 3
Classifier: License :: OSI Approved :: MIT License
License-File: LICENSE
Requires-Dist: numpy
Requires-Dist: scipy
Requires-Dist: astropy
Requires-Dist: pandas
Requires-Dist: matplotlib
